MkStepper/__init__.py
MkStepper-0.0.5.dist-info/LICENSE
MkStepper-0.0.5.dist-info/METADATA
MkStepper-0.0.5.dist-info/WHEEL
MkStepper-0.0.5.dist-info/top_level.txt
MkStepper-0.0.5.dist-info/RECORD
